MANIFEST.in
README.rst
djangotestxmlrpc.py
setup.py
djangotestxmlrpc.egg-info/PKG-INFO
djangotestxmlrpc.egg-info/SOURCES.txt
djangotestxmlrpc.egg-info/dependency_links.txt
djangotestxmlrpc.egg-info/not-zip-safe
djangotestxmlrpc.egg-info/top_level.txt