Metadata-Version: 1.1
Name: djangotestxmlrpc
Version: 0.0.2
Summary: Utility classes for testing Django views that speak XML-RPC
Home-page: https://github.com/msabramo/djangotestxmlrpc
Author: Marc Abramowitz
Author-email: marc@marc-abramowitz.com
License: MIT
Keywords: unittest,testing,Django,XML-RPC
Platform: UNKNOWN
Classifier: Programming Language :: Python :: 2
Classifier: Programming Language :: Python :: 2.5
Classifier: Programming Language :: Python :: 2.6
Classifier: Programming Language :: Python :: 2.7
Classifier: Programming Language :: Python :: 3
Classifier: Programming Language :: Python :: 3.1
Classifier: Programming Language :: Python :: 3.2
Classifier: Programming Language :: Python :: 3.3
Classifier: Topic :: Software Development :: Testing
Classifier: Natural Language :: English
Classifier: Intended Audience :: Developers
